{
  "users": [
    {
      "name": "Gitesh",
      "email": "Gitesh@Gitesh.com",
      "phone": "8789798798",
      "country": "USA",
      "status": "Active",
      "id": 1
    },
    {
      "name": "Edit123213",
      "email": "User Details",
      "phone": "User Details",
      "country": "User Details",
      "status": "In-Active",
      "id": 7
    },
    {
      "name": "Sort check",
      "email": "sort check",
      "phone": "sort check",
      "country": "sort check",
      "status": "Active",
      "id": 11
    },
    {
      "name": "Psort",
      "email": "Psort",
      "phone": "Psort",
      "country": "Psort",
      "status": "In-Active",
      "id": 12
    },
    {
      "name": "22",
      "email": "22",
      "phone": "22",
      "country": "22",
      "status": "Active",
      "id": 2
    },
    {
      "name": "333333333333",
      "email": "33",
      "phone": "33",
      "country": "33",
      "status": "Active",
      "id": 3
    },
    {
      "name": "9999999",
      "email": "9edit",
      "phone": "9",
      "country": "9",
      "status": "Active",
      "id": 9
    },
    {
      "name": "9",
      "email": "9",
      "phone": "9",
      "country": "9",
      "status": "Active",
      "id": 24
    },
    {
      "name": "990000",
      "email": "9",
      "phone": "9",
      "country": "9",
      "status": "Active",
      "id": 27
    },
    {
      "name": "10",
      "email": "10",
      "phone": "10",
      "country": "10",
      "status": "Active",
      "id": 28
    },
    {
      "name": "NEW1",
      "email": "NEW1",
      "phone": "NEW1",
      "country": "NEW1",
      "status": "In-Active",
      "id": 29
    },
    {
      "name": "New2",
      "email": "New2",
      "phone": "New2",
      "country": "New2",
      "status": "In-Active",
      "id": 30
    },
    {
      "name": "New3",
      "email": "New3",
      "phone": "New3",
      "country": "New3",
      "status": "Active",
      "id": 31
    },
    {
      "name": "Add User Status",
      "email": "Add User Status",
      "phone": "Add User Status",
      "country": "Add User Status",
      "status": "In-Active",
      "id": 32
    },
    {
      "name": "N555",
      "email": "N55555",
      "phone": "N555E",
      "country": "N56",
      "status": "In-Active",
      "id": 33
    },
    {
      "name": "N66",
      "email": "N66",
      "phone": "N66",
      "country": "N66",
      "status": "Active",
      "id": 34
    },
    {
      "name": "N7",
      "email": "N7",
      "phone": "N7",
      "country": "N7",
      "status": "In-Active",
      "id": 35
    }
  ]
}